ppry/__init__.py
ppry-2.0.0.dist-info/METADATA
ppry-2.0.0.dist-info/WHEEL
ppry-2.0.0.dist-info/top_level.txt
ppry-2.0.0.dist-info/RECORD
